zynq/axi4_systolic_array.v
`timescale 1ns / 1ps

module axi4_systolic_array #(
    parameter SIZE = 32
)(
    input wire clk,
    input wire resetn,
    // AXI4-Lite slave interface
    input wire [31:0] s_axi_awaddr,
    input wire s_axi_awvalid,
    output reg s_axi_awready,
    input wire [31:0] s_axi_wdata,
    input wire [3:0] s_axi_wstrb,
    input wire s_axi_wvalid,
    output reg s_axi_wready,
    output reg [1:0] s_axi_bresp,
    output reg s_axi_bvalid,
    input wire s_axi_bready,
    input wire [31:0] s_axi_araddr,
    input wire s_axi_arvalid,
    output reg s_axi_arready,
    output reg [31:0] s_axi_rdata,
    output reg [1:0] s_axi_rresp,
    output reg s_axi_rvalid,
    input wire s_axi_rready,
    // Convolution control
    output reg done,
    // Memory interfaces for kernel and world
    input wire [31:0] kernel_data,
    output reg kernel_read,
    input wire [31:0] world_data,
    output reg world_read
);

// AXI4-Lite slave interface implementation

// Address decoding
localparam ADDR_KERNEL_BASE = 32'h0000_0000;
localparam ADDR_WORLD_BASE  = 32'h0000_1000;
localparam ADDR_CONTROL     = 32'h0000_2000;
localparam ADDR_RESULT_BASE = 32'h0000_3000;

// AXI4-Lite slave interface state machine
localparam IDLE = 2'b00;
localparam WRITE = 2'b01;
localparam READ = 2'b10;

reg [1:0] state;
reg [31:0] awaddr_reg, araddr_reg;
reg [31:0] wdata_reg;
reg [3:0] wstrb_reg;
reg [7:0] kernel_index;
reg [7:0] world_index;

// Systolic array for convolution
reg [31:0] kernel [0:SIZE-1][0:SIZE-1];
reg [31:0] world [0:SIZE-1][0:SIZE-1];
reg [31:0] result [0:SIZE-1][0:SIZE-1];
reg [31:0] tmp;

integer i, j, k, l;

// Load kernel and world data
always @(posedge clk) begin
    if (!resetn) begin
        // Reset
        kernel_read <= 0;
        world_read <= 0;
        kernel_index <= 0;
        world_index <= 0;
        i <= 0;
        j <= 0;
        k <= 0;
        l <= 0;
    end else begin
        if (kernel_read) begin
            kernel[kernel_index / SIZE][kernel_index % SIZE] <= kernel_data;
            kernel_index <= kernel_index + 1;
        end

        if (world_read) begin
            world[world_index / SIZE][world_index % SIZE] <= world_data;
            world_index <= world_index + 1;
        end
    end
end
integer x, y;
// Convolution operation
always @(posedge clk) begin
    if (!resetn) begin
        // Reset
        done <= 0;
        x <= 0;
        y <= 0;
        tmp <= 0;
    end else if (state == IDLE && s_axi_wvalid && s_axi_wready) begin
        // Perform convolution
        for (i = 0; i < SIZE; i = i + 1) begin
            for (j = 0; j < SIZE; j = j + 1) begin
                result[i][j] <= 0;
                for (k = 0; k < SIZE; k = k + 1) begin
                    for (l = 0; l < SIZE; l = l + 1) begin
                        x = i + k - SIZE / 2;
                        y = j + l - SIZE / 2;
                        if (0 <= x && x < SIZE && 0 <= y && y < SIZE) begin
                            result[i][j] <= result[i][j] + kernel[k][l] * world[x][y];
                            tmp <= result[i][j]+i;
                        end
                    end
                end
            end
        end
        done <= 1;
    end else begin
        done <= 0;
    end
end

integer index;
// AXI4-Lite slave interface logic
always @(posedge clk) begin
    if (!resetn) begin
        state <= IDLE;
        s_axi_awready <= 1'b0;
        s_axi_wready <= 1'b0;
        s_axi_bvalid <= 1'b0;
        s_axi_bresp <= 2'b00;
        s_axi_arready <= 1'b0;
        s_axi_rvalid <= 1'b0;
        s_axi_rresp <= 2'b00;
        awaddr_reg <= 32'b0;
        araddr_reg <= 32'b0;
        wdata_reg <= 32'b0;
        wstrb_reg <= 4'b0;
        index <= 0;
        s_axi_rdata <= 0;
    end else begin
        case (state)
            IDLE: begin
                if (s_axi_awvalid && !s_axi_awready) begin
                    s_axi_awready <= 1'b1;
                    awaddr_reg <= s_axi_awaddr;
                    state <= WRITE;
                end else if (s_axi_arvalid && !s_axi_arready) begin
                    s_axi_arready <= 1'b1;
                    araddr_reg <= s_axi_araddr;
                    state <= READ;
                end
            end

            WRITE: begin
                s_axi_awready <= 1'b0;
                if (s_axi_wvalid && !s_axi_wready) begin
                    s_axi_wready <= 1'b1;
                    wdata_reg <= s_axi_wdata;
                    wstrb_reg <= s_axi_wstrb;
                end
                if (s_axi_wready && s_axi_wvalid) begin
                    s_axi_wready <= 1'b0;
                    s_axi_bvalid <= 1'b1;
                    s_axi_bresp <= 2'b00; // OKAY response
                    // Write data to the appropriate memory
                    if (awaddr_reg >= ADDR_KERNEL_BASE && awaddr_reg < ADDR_KERNEL_BASE + SIZE*SIZE*4) begin
                        kernel_read <= 1'b1;
                    end else if (awaddr_reg >= ADDR_WORLD_BASE && awaddr_reg < ADDR_WORLD_BASE + SIZE*SIZE*4) begin
                        world_read <= 1'b1;
                    end else if (awaddr_reg == ADDR_CONTROL) begin
                        // Control register write (e.g., start convolution)
                        if (wdata_reg[0]) begin
                            // Trigger convolution
                            state <= IDLE;
                        end
                    end
                end
                if (s_axi_bready && s_axi_bvalid) begin
                    s_axi_bvalid <= 1'b0;
                    state <= IDLE;
                end
            end

            READ: begin
                s_axi_arready <= 1'b0;
                if (!s_axi_rvalid) begin
                    s_axi_rvalid <= 1'b1;
                    s_axi_rresp <= 2'b00; // OKAY response
                    // Read data from the appropriate memory
                    if (araddr_reg >= ADDR_RESULT_BASE && araddr_reg < ADDR_RESULT_BASE + SIZE*SIZE*4) begin
                        index = (araddr_reg - ADDR_RESULT_BASE) / 4;
                        s_axi_rdata <= result[index / SIZE][index % SIZE];
                    end else begin
                        s_axi_rdata <= 32'b0;
                    end
                end
                if (s_axi_rready && s_axi_rvalid) begin
                    s_axi_rvalid <= 1'b0;
                    state <= IDLE;
                end
            end
        endcase
    end
end

endmodule

zynq/axi4_systolic_array_tb.v
`timescale 1ns / 1ps

//python file_monitor.py -f axi4_systolic_array.v -f axi4_systolic_array_tb.v -t 0.1
/*
module axi4_systolic_array_tb;

    // Testbench parameters
    parameter SIZE = 4;

    // Clock and reset signals
    reg clk;
    reg resetn;

    // AXI4-Lite slave interface signals
    reg [31:0] s_axi_awaddr;
    reg s_axi_awvalid;
    wire s_axi_awready;
    reg [31:0] s_axi_wdata;
    reg [3:0] s_axi_wstrb;
    reg s_axi_wvalid;
    wire s_axi_wready;
    wire [1:0] s_axi_bresp;
    wire s_axi_bvalid;
    reg s_axi_bready;
    reg [31:0] s_axi_araddr;
    reg s_axi_arvalid;
    wire s_axi_arready;
    wire [31:0] s_axi_rdata;
    wire [1:0] s_axi_rresp;
    wire s_axi_rvalid;
    reg s_axi_rready;

    // Systolic array instance
    axi4_systolic_array #(
        .SIZE(SIZE)
    ) uut (
        .clk(clk),
        .resetn(resetn),
        .s_axi_awaddr(s_axi_awaddr),
        .s_axi_awvalid(s_axi_awvalid),
        .s_axi_awready(s_axi_awready),
        .s_axi_wdata(s_axi_wdata),
        .s_axi_wstrb(s_axi_wstrb),
        .s_axi_wvalid(s_axi_wvalid),
        .s_axi_wready(s_axi_wready),
        .s_axi_bresp(s_axi_bresp),
        .s_axi_bvalid(s_axi_bvalid),
        .s_axi_bready(s_axi_bready),
        .s_axi_araddr(s_axi_araddr),
        .s_axi_arvalid(s_axi_arvalid),
        .s_axi_arready(s_axi_arready),
        .s_axi_rdata(s_axi_rdata),
        .s_axi_rresp(s_axi_rresp),
        .s_axi_rvalid(s_axi_rvalid),
        .s_axi_rready(s_axi_rready),
        .done(done)
    );

    // Clock generation
    initial begin
        clk = 0;
        forever #5 clk = ~clk; // 100MHz clock
    end
    
    integer i, j, idx;
    // Test procedure
    initial begin
        $dumpfile( "axi4_systolic_array_tb.vcd" );
        $dumpvars( 0, axi4_systolic_array_tb );
        //for (idx = 0; idx < 2; idx = idx + 1) $dumpvars(0, uut.result[idx][0]); 
        // Initialize signals
        resetn = 0;
        s_axi_awaddr = 0;
        s_axi_awvalid = 0;
        s_axi_wdata = 0;
        s_axi_wstrb = 4'b1111;
        s_axi_wvalid = 0;
        s_axi_bready = 0;
        s_axi_araddr = 0;
        s_axi_arvalid = 0;
        s_axi_rready = 0;

        // Apply reset
        #10;
        resetn = 1;
        #10;

        // Write kernel data
        for (i = 0; i < SIZE; i++) begin
            for ( j = 0; j < SIZE; j++) begin
                axi_write(32'h0000_0000 + ((i * SIZE + j) * 4), i + j);
            end
        end

        // Write world data
        for (i = 0; i < SIZE; i++) begin
            for (j = 0; j < SIZE; j++) begin
                axi_write(32'h0000_1000 + ((i * SIZE + j) * 4), i * j);
            end
        end

        // Trigger convolution operation
        axi_write(32'h0000_2000, 32'h0000_0001);

        // Wait for convolution to complete
        #1000;

        // Read and check result data
        for (i = 0; i < SIZE; i++) begin
            for (j = 0; j < SIZE; j++) begin
                axi_read(32'h0000_3000 + ((i * SIZE + j) * 4));
            end
        end

        // End simulation
        //$stop;
        $finish;
    end

    // AXI write task
    task axi_write(input [31:0] addr, input [31:0] data);
        begin
            // Write address
            @(posedge clk);
            s_axi_awaddr = addr;
            s_axi_awvalid = 1;
            @(posedge clk);
            s_axi_awvalid = 0;

            // Write data
            @(posedge clk);
            s_axi_wdata = data;
            s_axi_wvalid = 1;
            @(posedge clk);
            s_axi_wvalid = 0;

            // Wait for write response
            s_axi_bready = 1;
            @(posedge clk);
            s_axi_bready = 0;
        end
    endtask

    // AXI read task
    task axi_read(input [31:0] addr);
        begin
            // Read address
            @(posedge clk);
            s_axi_araddr = addr;
            s_axi_arvalid = 1;
            @(posedge clk);
            s_axi_arvalid = 0;

            // Wait for read data
            s_axi_rready = 1;
            @(posedge clk);
            s_axi_rready = 0;

            // Display read data
            @(posedge clk);
            $display("Read Data from %h: %h", addr, s_axi_rdata);
        end
    endtask

endmodule
*/


/*
`timescale 1ns / 1ps

module axi4_systolic_array_tb;

    // Parameters
    parameter SIZE = 32;
    
    // Inputs
    reg clk;
    reg resetn;
    reg [31:0] s_axi_awaddr;
    reg s_axi_awvalid;
    reg [31:0] s_axi_wdata;
    reg [3:0] s_axi_wstrb;
    reg s_axi_wvalid;
    reg s_axi_bready;
    reg [31:0] s_axi_araddr;
    reg s_axi_arvalid;
    reg s_axi_rready;
    reg [31:0] kernel_data;
    reg [31:0] world_data;

    // Outputs
    wire s_axi_awready;
    wire s_axi_wready;
    wire [1:0] s_axi_bresp;
    wire s_axi_bvalid;
    wire s_axi_arready;
    wire [31:0] s_axi_rdata;
    wire [1:0] s_axi_rresp;
    wire s_axi_rvalid;
    wire done;
    wire kernel_read;
    wire world_read;

    // Instantiate the Unit Under Test (UUT)
    axi4_systolic_array #(SIZE) uut (
        .clk(clk), 
        .resetn(resetn), 
        .s_axi_awaddr(s_axi_awaddr), 
        .s_axi_awvalid(s_axi_awvalid), 
        .s_axi_awready(s_axi_awready), 
        .s_axi_wdata(s_axi_wdata), 
        .s_axi_wstrb(s_axi_wstrb), 
        .s_axi_wvalid(s_axi_wvalid), 
        .s_axi_wready(s_axi_wready), 
        .s_axi_bresp(s_axi_bresp), 
        .s_axi_bvalid(s_axi_bvalid), 
        .s_axi_bready(s_axi_bready), 
        .s_axi_araddr(s_axi_araddr), 
        .s_axi_arvalid(s_axi_arvalid), 
        .s_axi_arready(s_axi_arready), 
        .s_axi_rdata(s_axi_rdata), 
        .s_axi_rresp(s_axi_rresp), 
        .s_axi_rvalid(s_axi_rvalid), 
        .s_axi_rready(s_axi_rready), 
        .done(done), 
        .kernel_data(kernel_data), 
        .kernel_read(kernel_read), 
        .world_data(world_data), 
        .world_read(world_read)
    );

    // Clock generation
    initial begin
        clk = 0;
        forever #5 clk = ~clk; // 100 MHz clock
    end

    // Test sequence
    initial begin
        $dumpfile( "axi4_systolic_array_tb.vcd" );
        $dumpvars( 0, axi4_systolic_array_tb );
    
        // Initialize Inputs
        resetn = 0;
        s_axi_awaddr = 0;
        s_axi_awvalid = 0;
        s_axi_wdata = 0;
        s_axi_wstrb = 0;
        s_axi_wvalid = 0;
        s_axi_bready = 0;
        s_axi_araddr = 0;
        s_axi_arvalid = 0;
        s_axi_rready = 0;
        kernel_data = 0;
        world_data = 0;

        // Apply reset
        #10;
        resetn = 1;
        #10;
        resetn = 0;
        #20;
        resetn = 1;

        // Wait for the reset to be released
        #20;

        // Write kernel data
        s_axi_awaddr = 32'h0000_0000; // Address for kernel base
        s_axi_awvalid = 1;
        s_axi_wdata = 32'h0000_0001; // Example kernel data
        s_axi_wstrb = 4'b1111;
        s_axi_wvalid = 1;
        s_axi_bready = 1;

        #10;
        s_axi_awvalid = 0;
        s_axi_wvalid = 0;
        
        // Write world data
        s_axi_awaddr = 32'h0000_1000; // Address for world base
        s_axi_awvalid = 1;
        s_axi_wdata = 32'h0000_0002; // Example world data
        s_axi_wstrb = 4'b1111;
        s_axi_wvalid = 1;

        #10;
        s_axi_awvalid = 0;
        s_axi_wvalid = 0;

        // Start convolution
        s_axi_awaddr = 32'h0000_2000; // Address for control
        s_axi_awvalid = 1;
        s_axi_wdata = 32'h0000_0001; // Start signal
        s_axi_wstrb = 4'b1111;
        s_axi_wvalid = 1;

        #10;
        s_axi_awvalid = 0;
        s_axi_wvalid = 0;

        // Wait for convolution to complete
        wait(done);

        // Read result data
        s_axi_araddr = 32'h0000_3000; // Address for result base
        s_axi_arvalid = 1;
        s_axi_rready = 1;

        #10;
        s_axi_arvalid = 0;

        // Wait for read valid signal
        wait(s_axi_rvalid);
        
        // Display the result
        $display("Result: %h", s_axi_rdata);

        // Finish simulation
        #100;
        $finish;
    end
endmodule

*/

`timescale 1ns / 1ps

module axi4_systolic_array_tb;
    // Parameters
    localparam SIZE = 3;

    // Signals
    reg clk;
    reg resetn;
    reg [31:0] s_axi_awaddr;
    reg s_axi_awvalid;
    wire s_axi_awready;
    reg [31:0] s_axi_wdata;
    reg [3:0] s_axi_wstrb;
    reg s_axi_wvalid;
    wire s_axi_wready;
    wire [1:0] s_axi_bresp;
    wire s_axi_bvalid;
    reg s_axi_bready;
    reg [31:0] s_axi_araddr;
    reg s_axi_arvalid;
    wire s_axi_arready;
    wire [31:0] s_axi_rdata;
    wire [1:0] s_axi_rresp;
    wire s_axi_rvalid;
    reg s_axi_rready;
    wire done;
    reg [31:0] kernel_data;
    wire kernel_read;
    reg [31:0] world_data;
    wire world_read;

    // Instantiate the unit under test (UUT)
    axi4_systolic_array #(
        .SIZE(SIZE)
    ) uut (
        .clk(clk),
        .resetn(resetn),
        .s_axi_awaddr(s_axi_awaddr),
        .s_axi_awvalid(s_axi_awvalid),
        .s_axi_awready(s_axi_awready),
        .s_axi_wdata(s_axi_wdata),
        .s_axi_wstrb(s_axi_wstrb),
        .s_axi_wvalid(s_axi_wvalid),
        .s_axi_wready(s_axi_wready),
        .s_axi_bresp(s_axi_bresp),
        .s_axi_bvalid(s_axi_bvalid),
        .s_axi_bready(s_axi_bready),
        .s_axi_araddr(s_axi_araddr),
        .s_axi_arvalid(s_axi_arvalid),
        .s_axi_arready(s_axi_arready),
        .s_axi_rdata(s_axi_rdata),
        .s_axi_rresp(s_axi_rresp),
        .s_axi_rvalid(s_axi_rvalid),
        .s_axi_rready(s_axi_rready),
        .done(done),
        .kernel_data(kernel_data),
        .kernel_read(kernel_read),
        .world_data(world_data),
        .world_read(world_read)
    );

    // Clock generation
    initial begin
        clk = 0;
        forever #5 clk = ~clk; // 100 MHz clock
    end
    integer i; 
    // Testbench logic
    initial begin
        $dumpfile( "axi4_systolic_array_tb.vcd" );
        $dumpvars( 0, axi4_systolic_array_tb );
        
        // Initialize signals
        resetn = 0;
        s_axi_awaddr = 0;
        s_axi_awvalid = 0;
        s_axi_wdata = 0;
        s_axi_wstrb = 0;
        s_axi_wvalid = 0;
        s_axi_bready = 0;
        s_axi_araddr = 0;
        s_axi_arvalid = 0;
        s_axi_rready = 0;
        kernel_data = 0;
        world_data = 0;
        
        // Apply reset
        #10 resetn = 1;

        // Load kernel data
        s_axi_awaddr = 32'h0000_0000;
        for ( i = 0; i < SIZE * SIZE; i = i + 1) begin
            s_axi_awvalid = 1;
            s_axi_wdata = i + 1; // Example data
            s_axi_wvalid = 1;
            @(posedge clk);
            //while (!s_axi_awready || !s_axi_wready) @(posedge clk);
            #20
            s_axi_awvalid = 0;
            s_axi_wvalid = 0;
            @(posedge clk);
        end

        // Load world data
        s_axi_awaddr = 32'h0000_1000;
        for ( i = 0; i < SIZE * SIZE; i = i + 1) begin
            s_axi_awvalid = 1;
            s_axi_wdata = (i + 1) * 10; // Example data
            s_axi_wvalid = 1;
            @(posedge clk);
            //while (!s_axi_awready || !s_axi_wready) @(posedge clk);
            #20
            s_axi_awvalid = 0;
            s_axi_wvalid = 0;
            @(posedge clk);
        end

        // Trigger convolution
        s_axi_awaddr = 32'h0000_2000;
        s_axi_awvalid = 1;
        s_axi_wdata = 1; // Start convolution
        s_axi_wvalid = 1;
        @(posedge clk);
        //while (!s_axi_awready || !s_axi_wready) @(posedge clk);
        #20
        s_axi_awvalid = 0;
        s_axi_wvalid = 0;
        @(posedge clk);

        // Wait for done signal
        //while (!done) @(posedge clk);
        #100

        // Read and verify results
        s_axi_araddr = 32'h0000_3000;
        for ( i = 0; i < SIZE * SIZE; i = i + 1) begin
            s_axi_arvalid = 1;
            @(posedge clk);
            //while (!s_axi_arready) @(posedge clk);
            #20
            s_axi_arvalid = 0;
            //while (!s_axi_rvalid) @(posedge clk);
            #20
            s_axi_rready = 1;
            @(posedge clk);
            s_axi_rready = 0;
            // Check s_axi_rdata against expected value here
            $display("Result[%0d] = %d", i, s_axi_rdata);
        end
 
        // Finish simulation
        $finish;
    end
endmodule

zynq/axi4_systolic_array_tb.vcd
$date
	Thu May 30 21:11:01 2024
$end
$version
	Icarus Verilog
$end
$timescale
	1ps
$end
$scope module axi4_systolic_array_tb $end
$var wire 1 ! world_read $end
$var wire 1 " s_axi_wready $end
$var wire 1 # s_axi_rvalid $end
$var wire 2 $ s_axi_rresp [1:0] $end
$var wire 32 % s_axi_rdata [31:0] $end
$var wire 1 & s_axi_bvalid $end
$var wire 2 ' s_axi_bresp [1:0] $end
$var wire 1 ( s_axi_awready $end
$var wire 1 ) s_axi_arready $end
$var wire 1 * kernel_read $end
$var wire 1 + done $end
$var parameter 32 , SIZE $end
$var reg 1 - clk $end
$var reg 32 . kernel_data [31:0] $end
$var reg 1 / resetn $end
$var reg 32 0 s_axi_araddr [31:0] $end
$var reg 1 1 s_axi_arvalid $end
$var reg 32 2 s_axi_awaddr [31:0] $end
$var reg 1 3 s_axi_awvalid $end
$var reg 1 4 s_axi_bready $end
$var reg 1 5 s_axi_rready $end
$var reg 32 6 s_axi_wdata [31:0] $end
$var reg 4 7 s_axi_wstrb [3:0] $end
$var reg 1 8 s_axi_wvalid $end
$var reg 32 9 world_data [31:0] $end
$var integer 32 : i [31:0] $end
$scope module uut $end
$var wire 1 - clk $end
$var wire 32 ; kernel_data [31:0] $end
$var wire 1 / resetn $end
$var wire 32 < s_axi_araddr [31:0] $end
$var wire 1 1 s_axi_arvalid $end
$var wire 32 = s_axi_awaddr [31:0] $end
$var wire 1 3 s_axi_awvalid $end
$var wire 1 4 s_axi_bready $end
$var wire 1 5 s_axi_rready $end
$var wire 32 > s_axi_wdata [31:0] $end
$var wire 4 ? s_axi_wstrb [3:0] $end
$var wire 1 8 s_axi_wvalid $end
$var wire 32 @ world_data [31:0] $end
$var parameter 32 A ADDR_CONTROL $end
$var parameter 32 B ADDR_KERNEL_BASE $end
$var parameter 32 C ADDR_RESULT_BASE $end
$var parameter 32 D ADDR_WORLD_BASE $end
$var parameter 2 E IDLE $end
$var parameter 2 F READ $end
$var parameter 32 G SIZE $end
$var parameter 2 H WRITE $end
$var reg 32 I araddr_reg [31:0] $end
$var reg 32 J awaddr_reg [31:0] $end
$var reg 1 + done $end
$var reg 8 K kernel_index [7:0] $end
$var reg 1 * kernel_read $end
$var reg 1 ) s_axi_arready $end
$var reg 1 ( s_axi_awready $end
$var reg 2 L s_axi_bresp [1:0] $end
$var reg 1 & s_axi_bvalid $end
$var reg 32 M s_axi_rdata [31:0] $end
$var reg 2 N s_axi_rresp [1:0] $end
$var reg 1 # s_axi_rvalid $end
$var reg 1 " s_axi_wready $end
$var reg 2 O state [1:0] $end
$var reg 32 P tmp [31:0] $end
$var reg 32 Q wdata_reg [31:0] $end
$var reg 8 R world_index [7:0] $end
$var reg 1 ! world_read $end
$var reg 4 S wstrb_reg [3:0] $end
$var integer 32 T i [31:0] $end
$var integer 32 U index [31:0] $end
$var integer 32 V j [31:0] $end
$var integer 32 W k [31:0] $end
$var integer 32 X l [31:0] $end
$var integer 32 Y x [31:0] $end
$var integer 32 Z y [31:0] $end
$upscope $end
$upscope $end
$enddefinitions $end
$comment Show the parameter values. $end
$dumpall
b1 H
b11 G
b10 F
b0 E
b1000000000000 D
b11000000000000 C
b0 B
b10000000000000 A
b11 ,
$end
#0
$dumpvars
bx Z
bx Y
bx X
bx W
bx V
bx U
bx T
bx S
bx R
bx Q
bx P
bx O
bx N
bx M
bx L
bx K
bx J
bx I
b0 @
b0 ?
b0 >
b0 =
b0 <
b0 ;
bx :
b0 9
08
b0 7
b0 6
05
04
03
b0 2
01
b0 0
0/
b0 .
0-
x+
x*
x)
x(
bx '
x&
bx %
bx $
x#
x"
x!
$end
#5000
b0 X
b0 W
b0 V
b0 T
b0 R
b0 K
0!
0*
b0 P
b0 Z
b0 Y
0+
b0 %
b0 M
b0 U
b0 S
b0 Q
b0 I
b0 J
b0 $
b0 N
0#
0)
b0 '
b0 L
0&
0"
0(
b0 O
1-
#10000
0-
18
b1 6
b1 >
13
b0 :
1/
#15000
b1 O
1(
1-
#20000
0-
#25000
b1 Q
1"
0(
1-
#30000
0-
#35000
1*
1&
0"
b10 6
b10 >
b1 :
1-
18
13
#40000
0-
#45000
b1 K
b10 Q
1"
1-
#50000
0-
#55000
0"
b10 K
1-
#60000
0-
#65000
b11 K
b11 Q
1"
b11 6
b11 >
b10 :
1-
18
13
#70000
0-
#75000
0"
b100 K
1-
#80000
0-
#85000
b101 K
1"
1-
#90000
0-
#95000
0"
b110 K
b100 6
b100 >
b11 :
1-
18
13
#100000
0-
#105000
b111 K
b100 Q
1"
1-
#110000
0-
#115000
0"
b1000 K
1-
#120000
0-
#125000
b1001 K
b101 Q
1"
b101 6
b101 >
b100 :
1-
18
13
#130000
0-
#135000
0"
b1010 K
1-
#140000
0-
#145000
b1011 K
1"
1-
#150000
0-
#155000
0"
b1100 K
b110 6
b110 >
b101 :
1-
18
13
#160000
0-
#165000
b1101 K
b110 Q
1"
1-
#170000
0-
#175000
0"
b1110 K
1-
#180000
0-
#185000
b1111 K
b111 Q
1"
b111 6
b111 >
b110 :
1-
18
13
#190000
0-
#195000
0"
b10000 K
1-
#200000
0-
#205000
b10001 K
1"
1-
#210000
0-
#215000
0"
b10010 K
b1000 6
b1000 >
b111 :
1-
18
13
#220000
0-
#225000
b10011 K
b1000 Q
1"
1-
#230000
0-
#235000
0"
b10100 K
1-
#240000
0-
#245000
b10101 K
b1001 Q
1"
b1001 6
b1001 >
b1000 :
1-
18
13
#250000
0-
#255000
0"
b10110 K
1-
#260000
0-
#265000
b10111 K
1"
1-
#270000
0-
#275000
0"
b11000 K
b1010 6
b1010 >
b1000000000000 2
b1000000000000 =
b0 :
1-
18
13
#280000
0-
#285000
b11001 K
b1010 Q
1"
1-
#290000
0-
#295000
0"
b11010 K
1-
#300000
0-
#305000
b11011 K
b10100 Q
1"
b10100 6
b10100 >
b1 :
1-
18
13
#310000
0-
#315000
0"
b11100 K
1-
#320000
0-
#325000
b11101 K
1"
1-
#330000
0-
#335000
0"
b11110 K
b11110 6
b11110 >
b10 :
1-
18
13
#340000
0-
#345000
b11111 K
b11110 Q
1"
1-
#350000
0-
#355000
0"
b100000 K
1-
#360000
0-
#365000
b100001 K
b101000 Q
1"
b101000 6
b101000 >
b11 :
1-
18
13
#370000
0-
#375000
0"
b100010 K
1-
#380000
0-
#385000
b100011 K
1"
1-
#390000
0-
#395000
0"
b100100 K
b110010 6
b110010 >
b100 :
1-
18
13
#400000
0-
#405000
b100101 K
b110010 Q
1"
1-
#410000
0-
#415000
0"
b100110 K
1-
#420000
0-
#425000
b100111 K
b111100 Q
1"
b111100 6
b111100 >
b101 :
1-
18
13
#430000
0-
#435000
0"
b101000 K
1-
#440000
0-
#445000
b101001 K
1"
1-
#450000
0-
#455000
0"
b101010 K
b1000110 6
b1000110 >
b110 :
1-
18
13
#460000
0-
#465000
b101011 K
b1000110 Q
1"
1-
#470000
0-
#475000
0"
b101100 K
1-
#480000
0-
#485000
b101101 K
b1010000 Q
1"
b1010000 6
b1010000 >
b111 :
1-
18
13
#490000
0-
#495000
0"
b101110 K
1-
#500000
0-
#505000
b101111 K
1"
1-
#510000
0-
#515000
0"
b110000 K
b1011010 6
b1011010 >
b1000 :
1-
18
13
#520000
0-
#525000
b110001 K
b1011010 Q
1"
1-
#530000
0-
#535000
0"
b110010 K
1-
#540000
0-
#545000
b110011 K
b1 Q
1"
b1 6
b1 >
b10000000000000 2
b10000000000000 =
b1001 :
1-
18
13
#550000
0-
#555000
0"
b110100 K
1-
#560000
0-
#565000
b110101 K
1"
1-
#570000
0-
#575000
b110110 K
1-
08
03
#580000
0-
#585000
b110111 K
1-
#590000
0-
#595000
b111000 K
1-
#600000
0-
#605000
b111001 K
1-
#610000
0-
#615000
b111010 K
1-
#620000
0-
#625000
b111011 K
1-
#630000
0-
#635000
b111100 K
1-
#640000
0-
#645000
b111101 K
1-
#650000
0-
#655000
b111110 K
1-
#660000
0-
#665000
b111111 K
1-
#670000
0-
#675000
b1000000 K
1-
11
b0 :
b11000000000000 0
b11000000000000 <
#680000
0-
#685000
b1000001 K
1-
#690000
0-
#695000
b1000010 K
1-
01
#700000
0-
#705000
b1000011 K
1-
#710000
0-
#715000
b1000100 K
11
b1 :
1-
05
#720000
0-
#725000
b1000101 K
1-
#730000
0-
#735000
b1000110 K
1-
#740000
0-
#745000
b1000111 K
1-
01
#750000
0-
#755000
b1001000 K
1-
#760000
0-
#765000
b1001001 K
11
b10 :
1-
05
#770000
0-
#775000
b1001010 K
1-
#780000
0-
#785000
b1001011 K
1-
#790000
0-
#795000
b1001100 K
1-
01
#800000
0-
#805000
b1001101 K
1-
#810000
0-
#815000
b1001110 K
11
b11 :
1-
05
#820000
0-
#825000
b1001111 K
1-
#830000
0-
#835000
b1010000 K
1-
#840000
0-
#845000
b1010001 K
1-
01
#850000
0-
#855000
b1010010 K
1-
#860000
0-
#865000
b1010011 K
11
b100 :
1-
05
#870000
0-
#875000
b1010100 K
1-
#880000
0-
#885000
b1010101 K
1-
#890000
0-
#895000
b1010110 K
1-
01
#900000
0-
#905000
b1010111 K
1-
#910000
0-
#915000
b1011000 K
11
b101 :
1-
05
#920000
0-
#925000
b1011001 K
1-
#930000
0-
#935000
b1011010 K
1-
#940000
0-
#945000
b1011011 K
1-
01
#950000
0-
#955000
b1011100 K
1-
#960000
0-
#965000
b1011101 K
11
b110 :
1-
05
#970000
0-
#975000
b1011110 K
1-
#980000
0-
#985000
b1011111 K
1-
#990000
0-
#995000
b1100000 K
1-
01
#1000000
0-
#1005000
b1100001 K
1-
#1010000
0-
#1015000
b1100010 K
11
b111 :
1-
05
#1020000
0-
#1025000
b1100011 K
1-
#1030000
0-
#1035000
b1100100 K
1-
#1040000
0-
#1045000
b1100101 K
1-
01
#1050000
0-
#1055000
b1100110 K
1-
#1060000
0-
#1065000
b1100111 K
11
b1000 :
1-
05
#1070000
0-
#1075000
b1101000 K
1-
#1080000
0-
#1085000
b1101001 K
1-
#1090000
0-
#1095000
b1101010 K
1-
01
#1100000
0-
#1105000
b1101011 K
1-
#1110000
0-
#1115000
b1101100 K
b1001 :
1-
05
