zynq/axi_convolution.v
module axi_convolution #(
  parameter integer C_S_AXI_DATA_WIDTH = 32,
  parameter integer C_S_AXI_ADDR_WIDTH = 7
)
(
  input wire  S_AXI_ACLK,
  input wire  S_AXI_ARESETN,
  input wire [C_S_AXI_ADDR_WIDTH-1 : 0] S_AXI_AWADDR,
  input wire  S_AXI_AWVALID,
  output wire  S_AXI_AWREADY,
  input wire [C_S_AXI_DATA_WIDTH-1 : 0] S_AXI_WDATA,
  input wire [(C_S_AXI_DATA_WIDTH/8)-1 : 0] S_AXI_WSTRB,
  input wire  S_AXI_WVALID,
  output wire  S_AXI_WREADY,
  output wire [1 : 0] S_AXI_BRESP,
  output wire  S_AXI_BVALID,
  input wire  S_AXI_BREADY,
  input wire [C_S_AXI_ADDR_WIDTH-1 : 0] S_AXI_ARADDR,
  input wire  S_AXI_ARVALID,
  output wire  S_AXI_ARREADY,
  output wire [C_S_AXI_DATA_WIDTH-1 : 0] S_AXI_RDATA,
  output wire [1 : 0] S_AXI_RRESP,
  output wire  S_AXI_RVALID,
  input wire  S_AXI_RREADY
);

    localparam integer ADDR_LSB = 2;
    localparam integer OPT_MEM_ADDR_BITS = 5;  // This depends on your address space size

  parameter integer SIZE = 3;
  
  // AXI4 Lite signals
  reg [C_S_AXI_ADDR_WIDTH-1 : 0] axi_awaddr;
  reg axi_awready;
  reg axi_wready;
  reg [1 : 0] axi_bresp;
  reg axi_bvalid;
  reg [C_S_AXI_ADDR_WIDTH-1 : 0] axi_araddr;
  reg axi_arready;
  reg [C_S_AXI_DATA_WIDTH-1 : 0] axi_rdata;
  reg [1 : 0] axi_rresp;
  reg axi_rvalid;

  // AXI4 Lite internal signals
  reg [C_S_AXI_DATA_WIDTH-1:0] reg_data_out;
  reg [C_S_AXI_DATA_WIDTH-1:0] slv_reg0;
  //reg slv_reg_wren;
  reg slv_reg_wren  = 1; //??
  
  // Registers to store kernel and world matrices
  reg [31:0] kernel [0:SIZE-1][0:SIZE-1];
  reg [31:0] world [0:SIZE-1][0:SIZE-1];
  reg [31:0] slv_reg_i;
  reg [31:0] slv_reg_j;
  reg start_convolution;
  reg [31:0] convolution_result;
  
  // Address decoding
  wire [C_S_AXI_ADDR_WIDTH-1:0] axi_addr;
  assign axi_addr = S_AXI_AWADDR;
  
  // I/O Connections assignments
  assign S_AXI_AWREADY = axi_awready;
  assign S_AXI_WREADY  = axi_wready;
  assign S_AXI_BRESP   = axi_bresp;
  assign S_AXI_BVALID  = axi_bvalid;
  assign S_AXI_ARREADY = axi_arready;
  assign S_AXI_RDATA   = axi_rdata;
  assign S_AXI_RRESP   = axi_rresp;
  assign S_AXI_RVALID  = axi_rvalid;

  // Implement axi_awready generation
  always @( posedge S_AXI_ACLK )
  begin
    if ( S_AXI_ARESETN == 1'b0 )
      begin
        axi_awready <= 1'b0;
      end 
    else
      begin    
        if (~axi_awready && S_AXI_AWVALID && S_AXI_WVALID)
          begin
            axi_awready <= 1'b1;
          end
        else           
          begin
            axi_awready <= 1'b0;
          end
      end 
  end       

  // Implement axi_wready generation
  always @( posedge S_AXI_ACLK )
  begin
    if ( S_AXI_ARESETN == 1'b0 )
      begin
        axi_wready <= 1'b0;
      end 
    else
      begin    
        if (~axi_wready && S_AXI_WVALID && S_AXI_AWVALID)
          begin
            axi_wready <= 1'b1;
          end
        else
          begin
            axi_wready <= 1'b0;
          end
      end 
  end       

  // Implement write response logic generation
  always @( posedge S_AXI_ACLK )
  begin
    if ( S_AXI_ARESETN == 1'b0 )
      begin
        axi_bvalid  <= 1'b0;
        axi_bresp   <= 2'b0;
      end 
    else
      begin    
        if (axi_awready && S_AXI_AWVALID && ~axi_bvalid && axi_wready && S_AXI_WVALID)
          begin
            axi_bvalid <= 1'b1;
            axi_bresp  <= 2'b0; // 'OKAY' response 
          end                   
        else
          begin
            if (S_AXI_BREADY && axi_bvalid) 
              begin
                axi_bvalid <= 1'b0; 
              end  
          end
      end
  end   

  // Implement axi_arready generation
  always @( posedge S_AXI_ACLK )
  begin
    if ( S_AXI_ARESETN == 1'b0 )
      begin
        axi_arready <= 1'b0;
        axi_araddr  <= 32'b0;
      end 
    else
      begin    
        if (~axi_arready && S_AXI_ARVALID)
          begin
            axi_arready <= 1'b1;
            axi_araddr  <= S_AXI_ARADDR;
          end
        else
          begin
            axi_arready <= 1'b0;
          end
      end 
  end       

  // Implement axi_rvalid generation
  always @( posedge S_AXI_ACLK )
  begin
    if ( S_AXI_ARESETN == 1'b0 )
      begin
        axi_rvalid <= 1'b0;
        axi_rresp  <= 2'b0;
      end 
    else
      begin    
        if (axi_arready && S_AXI_ARVALID && ~axi_rvalid)
          begin
            axi_rvalid <= 1'b1;
            axi_rresp  <= 2'b0; // 'OKAY' response
          end   
        else if (axi_rvalid && S_AXI_RREADY)
          begin
            axi_rvalid <= 1'b0;
          end                
      end
  end   

  // Implement memory mapped register select and read logic generation
  always @(*)
  begin
  $display("wwwww %d", axi_araddr );
    //case ( axi_araddr[ADDR_LSB+OPT_MEM_ADDR_BITS:ADDR_LSB] )
    //case ( axi_araddr[ADDR_LSB+OPT_MEM_ADDR_BITS:ADDR_LSB] )
    case ( axi_araddr )
      4'h0   : reg_data_out <= kernel[0][0];
      4'h1   : reg_data_out <= kernel[0][1];
      4'h2   : reg_data_out <= kernel[0][2];
      4'h3   : reg_data_out <= kernel[1][0];
      4'h4   : reg_data_out <= kernel[1][1];
      4'h5   : reg_data_out <= kernel[1][2];
      4'h6   : reg_data_out <= kernel[2][0];
      4'h7   : reg_data_out <= kernel[2][1];
      4'h8   : reg_data_out <= kernel[2][2];
      4'h9   : reg_data_out <= world[0][0];
      4'hA   : reg_data_out <= world[0][1];
      4'hB   : reg_data_out <= world[0][2];
      4'hC   : reg_data_out <= world[1][0];
      4'hD   : reg_data_out <= world[1][1];
      4'hE   : reg_data_out <= world[1][2];
      4'hF   : reg_data_out <= world[2][0];
      5'h10  : reg_data_out <= world[2][1];
      5'h11  : reg_data_out <= world[2][2];
      5'h12  : reg_data_out <= slv_reg_i;
      5'h13  : reg_data_out <= slv_reg_j;
      5'h14  : reg_data_out <= {31'b0, start_convolution};
      5'h15  : begin 
        reg_data_out <= convolution_result;
      $display("w222");
      end
      default: reg_data_out <= 0;
    endcase
  end

  // Output register or memory read data
  always @( posedge S_AXI_ACLK )
  begin
    if ( S_AXI_ARESETN == 1'b0 )
      begin
        axi_rdata  <= 0;
      end 
    else
      begin    
        if (axi_arready && S_AXI_ARVALID)
          begin
            axi_rdata <= reg_data_out;     
          end   
      end
  end   
integer m, n;
  // AXI write logic
  always @(posedge S_AXI_ACLK)
  begin
    if (S_AXI_ARESETN == 1'b0)
      begin
        
        for (m = 0; m < SIZE; m = m + 1)
          begin
            for (n = 0; n < SIZE; n = n + 1)
              begin
                kernel[m][n] <= 0;
                world[m][n] <= 0;
              end
          end
        slv_reg_i <= 0;
        slv_reg_j <= 0;
        start_convolution <= 0;
      end 
    else
      begin
        if (slv_reg_wren)
          begin
          //$display("qqq %d %d, %d", ADDR_LSB, OPT_MEM_ADDR_BITS, S_AXI_AWADDR );
            case (axi_awaddr)//[ADDR_LSB+OPT_MEM_ADDR_BITS:ADDR_LSB])
            //case (axi_awaddr[3:0])
              4'h0: kernel[0][0] <= S_AXI_WDATA;
              4: begin kernel[0][1] <= S_AXI_WDATA;
              $display("rrrrrr");
              end
              4'h8: kernel[0][2] <= S_AXI_WDATA;
              4'h3: kernel[1][0] <= S_AXI_WDATA;
              4'h4: kernel[1][1] <= S_AXI_WDATA;
              4'h5: kernel[1][2] <= S_AXI_WDATA;
              4'h6: kernel[2][0] <= S_AXI_WDATA;
              4'h7: kernel[2][1] <= S_AXI_WDATA;
              4'h8: kernel[2][2] <= S_AXI_WDATA;
              4'h9: world[0][0] <= S_AXI_WDATA;
              4'hA: world[0][1] <= S_AXI_WDATA;
              4'hB: world[0][2] <= S_AXI_WDATA;
              4'hC: world[1][0] <= S_AXI_WDATA;
              4'hD: world[1][1] <= S_AXI_WDATA;
              4'hE: world[1][2] <= S_AXI_WDATA;
              4'hF: world[2][0] <= S_AXI_WDATA;
              5'h10: world[2][1] <= S_AXI_WDATA;
              5'h11: world[2][2] <= S_AXI_WDATA;
              5'h12: slv_reg_i <= S_AXI_WDATA;
              5'h13: slv_reg_j <= S_AXI_WDATA;
              5'h14: start_convolution <= S_AXI_WDATA[0];
              default: ;
            endcase
          end
      end
  end
	integer k, l;
  integer x, y;
  reg [31:0] sum;
  // Convolution logic
  always @(posedge S_AXI_ACLK)
  begin
    if (S_AXI_ARESETN == 1'b0)
      begin
        convolution_result <= 0;
      end 
    else
      begin
        if (start_convolution)
          begin
            

            
            sum <= 0;
            for (k = 0; k < SIZE; k = k + 1)
              begin
                for (l = 0; l < SIZE; l = l + 1)
                  begin
                    x = slv_reg_i + k - SIZE/2;
                    y = slv_reg_j + l - SIZE/2;
                    if (0 <= x && x < SIZE && 0 <= y && y < SIZE)
                      begin
                        sum <= sum + kernel[k][l] * world[x][y];
                      end
                  end
              end
            convolution_result <= sum;
          end
      end
  end

endmodule

zynq/axi_convolution_tb.v
`timescale 1ns / 1ps

// cd C:\git\lenia_verilog\zynq
// python file_monitor.py -f axi_convolution.v -f axi_convolution_tb.v -t 0.1

module axi_convolution_tb;

  parameter integer C_S_AXI_DATA_WIDTH = 32;
  parameter integer C_S_AXI_ADDR_WIDTH = 7;
  parameter integer SIZE = 3;

  // Clock and Reset
  reg S_AXI_ACLK;
  reg S_AXI_ARESETN;

  // AXI4 Lite signals
  reg [C_S_AXI_ADDR_WIDTH-1 : 0] S_AXI_AWADDR;
  reg S_AXI_AWVALID;
  wire S_AXI_AWREADY;
  reg [C_S_AXI_DATA_WIDTH-1 : 0] S_AXI_WDATA;
  reg [(C_S_AXI_DATA_WIDTH/8)-1 : 0] S_AXI_WSTRB;
  reg S_AXI_WVALID;
  wire S_AXI_WREADY;
  wire [1 : 0] S_AXI_BRESP;
  wire S_AXI_BVALID;
  reg S_AXI_BREADY;
  reg [C_S_AXI_ADDR_WIDTH-1 : 0] S_AXI_ARADDR;
  reg S_AXI_ARVALID;
  wire S_AXI_ARREADY;
  wire [C_S_AXI_DATA_WIDTH-1 : 0] S_AXI_RDATA;
  wire [1 : 0] S_AXI_RRESP;
  wire S_AXI_RVALID;
  reg S_AXI_RREADY;

  // Instantiate the AXI Convolution module
  axi_convolution #(
    .C_S_AXI_DATA_WIDTH(C_S_AXI_DATA_WIDTH),
    .C_S_AXI_ADDR_WIDTH(C_S_AXI_ADDR_WIDTH)
  ) dut (
    .S_AXI_ACLK(S_AXI_ACLK),
    .S_AXI_ARESETN(S_AXI_ARESETN),
    .S_AXI_AWADDR(S_AXI_AWADDR),
    .S_AXI_AWVALID(S_AXI_AWVALID),
    .S_AXI_AWREADY(S_AXI_AWREADY),
    .S_AXI_WDATA(S_AXI_WDATA),
    .S_AXI_WSTRB(S_AXI_WSTRB),
    .S_AXI_WVALID(S_AXI_WVALID),
    .S_AXI_WREADY(S_AXI_WREADY),
    .S_AXI_BRESP(S_AXI_BRESP),
    .S_AXI_BVALID(S_AXI_BVALID),
    .S_AXI_BREADY(S_AXI_BREADY),
    .S_AXI_ARADDR(S_AXI_ARADDR),
    .S_AXI_ARVALID(S_AXI_ARVALID),
    .S_AXI_ARREADY(S_AXI_ARREADY),
    .S_AXI_RDATA(S_AXI_RDATA),
    .S_AXI_RRESP(S_AXI_RRESP),
    .S_AXI_RVALID(S_AXI_RVALID),
    .S_AXI_RREADY(S_AXI_RREADY)
  );

  // Clock generation
  initial begin
    S_AXI_ACLK = 0;
    forever #5 S_AXI_ACLK = ~S_AXI_ACLK;
  end

  // Reset generation
  initial begin
    S_AXI_ARESETN = 0;
    #20 S_AXI_ARESETN = 1;
    #20 S_AXI_ARESETN = 0;
    #20 S_AXI_ARESETN = 1;
 //   #20 S_AXI_ARESETN = 1;
  end

  // AXI write task
  task axi_write(
        input [C_S_AXI_ADDR_WIDTH-1:0] addr,
        input [C_S_AXI_DATA_WIDTH-1:0] data
    );
    begin
      $display("write %d %d", addr, data );
      @(posedge S_AXI_ACLK);
      S_AXI_AWADDR = addr;
      S_AXI_AWVALID = 1;
      S_AXI_WDATA = data;
      S_AXI_WSTRB = 4'b1111;
      S_AXI_WVALID = 1;

      while (~S_AXI_AWREADY || ~S_AXI_WREADY) @(posedge S_AXI_ACLK);
      S_AXI_AWVALID = 0;
      S_AXI_WVALID = 0;
      @(posedge S_AXI_ACLK);
      S_AXI_BREADY = 1;
      while (~S_AXI_BVALID) @(posedge S_AXI_ACLK);
      S_AXI_BREADY = 0;
    end
  endtask

  // AXI read task
  task axi_read( 
        input [C_S_AXI_ADDR_WIDTH-1:0] addr,
        output [C_S_AXI_DATA_WIDTH-1:0] data
    );
    begin
      @(posedge S_AXI_ACLK);
      S_AXI_ARADDR = addr;
      S_AXI_ARVALID = 1;
      while (~S_AXI_ARREADY) @(posedge S_AXI_ACLK);
      S_AXI_ARVALID = 0;
      @(posedge S_AXI_ACLK);
      S_AXI_RREADY = 1;
      while (~S_AXI_RVALID) @(posedge S_AXI_ACLK);
      data = S_AXI_RDATA;
      S_AXI_RREADY = 0;
      $display("read %d %d", addr, data );
    end
  endtask

initial begin
    $dumpfile( "axi_convolution_tb.vcd" );
    $dumpvars( 0, axi_convolution_tb );
    
    #2000;
    $display("finish");
    $finish;
end
reg [C_S_AXI_DATA_WIDTH-1:0] result;
  // Stimulus
  initial begin
    // Wait for reset deassertion
    $display("reset");
    S_AXI_AWADDR = 0;
    @(negedge S_AXI_ARESETN);
    @(posedge S_AXI_ARESETN);
    #40

    // Write kernel values
    $display("write kernel");
    axi_write(7'h00, 32'h00000001); // kernel[0][0] = 1
    axi_write(7'h04, 32'h00000002); // kernel[0][1] = 2
    axi_write(7'h08, 32'h00000003); // kernel[0][2] = 3
    axi_write(7'h0C, 32'h00000004); // kernel[1][0] = 4
    axi_write(7'h10, 32'h00000005); // kernel[1][1] = 5
    axi_write(7'h14, 32'h00000006); // kernel[1][2] = 6
    axi_write(7'h18, 32'h00000007); // kernel[2][0] = 7
    axi_write(7'h1C, 32'h00000008); // kernel[2][1] = 8
    axi_write(7'h20, 32'h00000009); // kernel[2][2] = 9
    #40
    
    // Write world values
    $display("write world");
    axi_write(7'h24, 32'h00000001); // world[0][0] = 1
    axi_write(7'h28, 32'h00000002); // world[0][1] = 2
    axi_write(7'h2C, 32'h00000003); // world[0][2] = 3
    axi_write(7'h30, 32'h00000004); // world[1][0] = 4
    axi_write(7'h34, 32'h00000005); // world[1][1] = 5
    axi_write(7'h38, 32'h00000006); // world[1][2] = 6
    axi_write(7'h3C, 32'h00000007); // world[2][0] = 7
    axi_write(7'h40, 32'h00000008); // world[2][1] = 8
    axi_write(7'h44, 32'h00000009); // world[2][2] = 9
    #40

    // Write indices i and j
    $display("write indexes");
    axi_write(7'h48, 32'h00000001); // i = 1
    axi_write(7'h4C, 32'h00000001); // j = 1
    #40

    // Start convolution
    $display("start");
    axi_write(7'h50, 32'h00000001); // start_convolution = 1
    #40

    // Wait for the convolution to complete
    #40;

    // Read convolution result
    
    $display("read");
    axi_read(7'h54, result);
    #40

    // Display result
    $display("44Convolution result: %d", result);

    // Finish simulation
    //$stop;
    $display("finish");
    $finish;
  end

endmodule

zynq/axi_convolution_tb.vcd
$date
	Sun Jun 02 18:35:24 2024
$end
$version
	Icarus Verilog
$end
$timescale
	1ps
$end
$scope module axi_convolution_tb $end
$var wire 1 ! S_AXI_WREADY $end
$var wire 1 " S_AXI_RVALID $end
$var wire 2 # S_AXI_RRESP [1:0] $end
$var wire 32 $ S_AXI_RDATA [31:0] $end
$var wire 1 % S_AXI_BVALID $end
$var wire 2 & S_AXI_BRESP [1:0] $end
$var wire 1 ' S_AXI_AWREADY $end
$var wire 1 ( S_AXI_ARREADY $end
$var parameter 32 ) C_S_AXI_ADDR_WIDTH $end
$var parameter 32 * C_S_AXI_DATA_WIDTH $end
$var parameter 32 + SIZE $end
$var reg 1 , S_AXI_ACLK $end
$var reg 7 - S_AXI_ARADDR [6:0] $end
$var reg 1 . S_AXI_ARESETN $end
$var reg 1 / S_AXI_ARVALID $end
$var reg 7 0 S_AXI_AWADDR [6:0] $end
$var reg 1 1 S_AXI_AWVALID $end
$var reg 1 2 S_AXI_BREADY $end
$var reg 1 3 S_AXI_RREADY $end
$var reg 32 4 S_AXI_WDATA [31:0] $end
$var reg 4 5 S_AXI_WSTRB [3:0] $end
$var reg 1 6 S_AXI_WVALID $end
$var reg 32 7 result [31:0] $end
$scope module dut $end
$var wire 1 , S_AXI_ACLK $end
$var wire 7 8 S_AXI_ARADDR [6:0] $end
$var wire 1 . S_AXI_ARESETN $end
$var wire 1 ( S_AXI_ARREADY $end
$var wire 1 / S_AXI_ARVALID $end
$var wire 7 9 S_AXI_AWADDR [6:0] $end
$var wire 1 ' S_AXI_AWREADY $end
$var wire 1 1 S_AXI_AWVALID $end
$var wire 1 2 S_AXI_BREADY $end
$var wire 2 : S_AXI_BRESP [1:0] $end
$var wire 1 % S_AXI_BVALID $end
$var wire 32 ; S_AXI_RDATA [31:0] $end
$var wire 1 3 S_AXI_RREADY $end
$var wire 2 < S_AXI_RRESP [1:0] $end
$var wire 1 " S_AXI_RVALID $end
$var wire 32 = S_AXI_WDATA [31:0] $end
$var wire 1 ! S_AXI_WREADY $end
$var wire 4 > S_AXI_WSTRB [3:0] $end
$var wire 1 6 S_AXI_WVALID $end
$var wire 7 ? axi_addr [6:0] $end
$var parameter 32 @ ADDR_LSB $end
$var parameter 32 A C_S_AXI_ADDR_WIDTH $end
$var parameter 32 B C_S_AXI_DATA_WIDTH $end
$var parameter 32 C OPT_MEM_ADDR_BITS $end
$var parameter 32 D SIZE $end
$var reg 7 E axi_araddr [6:0] $end
$var reg 1 F axi_arready $end
$var reg 7 G axi_awaddr [6:0] $end
$var reg 1 H axi_awready $end
$var reg 2 I axi_bresp [1:0] $end
$var reg 1 J axi_bvalid $end
$var reg 32 K axi_rdata [31:0] $end
$var reg 2 L axi_rresp [1:0] $end
$var reg 1 M axi_rvalid $end
$var reg 1 N axi_wready $end
$var reg 32 O convolution_result [31:0] $end
$var reg 32 P reg_data_out [31:0] $end
$var reg 32 Q slv_reg_i [31:0] $end
$var reg 32 R slv_reg_j [31:0] $end
$var reg 1 S slv_reg_wren $end
$var reg 1 T start_convolution $end
$var reg 32 U sum [31:0] $end
$var integer 32 V k [31:0] $end
$var integer 32 W l [31:0] $end
$var integer 32 X m [31:0] $end
$var integer 32 Y n [31:0] $end
$var integer 32 Z x [31:0] $end
$var integer 32 [ y [31:0] $end
$upscope $end
$scope task axi_read $end
$var reg 7 \ addr [6:0] $end
$var reg 32 ] data [31:0] $end
$upscope $end
$scope task axi_write $end
$var reg 7 ^ addr [6:0] $end
$var reg 32 _ data [31:0] $end
$upscope $end
$upscope $end
$enddefinitions $end
$comment Show the parameter values. $end
$dumpall
b11 D
b101 C
b100000 B
b111 A
b10 @
b11 +
b100000 *
b111 )
$end
#0
$dumpvars
bx _
bx ^
bx ]
bx \
bx [
bx Z
bx Y
bx X
bx W
bx V
bx U
xT
1S
bx R
bx Q
bx P
bx O
xN
xM
bx L
bx K
xJ
bx I
xH
bx G
xF
bx E
b0 ?
bx >
bx =
bx <
bx ;
bx :
b0 9
bx 8
bx 7
x6
bx 5
bx 4
x3
x2
x1
b0 0
x/
0.
bx -
0,
x(
x'
bx &
x%
bx $
bx #
x"
x!
$end
#5000
b0 P
0'
0H
0!
0N
b0 &
b0 :
b0 I
0%
0J
b0 E
0(
0F
b0 #
b0 <
b0 L
0"
0M
b0 $
b0 ;
b0 K
0T
b0 R
b0 Q
b0 O
b11 Y
b11 X
1,
#10000
0,
#15000
b11 Y
b11 X
1,
#20000
0,
1.
#25000
1,
#30000
0,
#35000
1,
#40000
0,
0.
#45000
b11 Y
b11 X
1,
#50000
0,
#55000
b11 Y
b11 X
1,
#60000
0,
1.
#65000
1,
#70000
0,
#75000
1,
#80000
0,
#85000
1,
#90000
0,
#95000
1,
#100000
0,
b1 _
b0 ^
#105000
1'
1H
1!
1N
16
b1111 5
b1111 >
b1 4
b1 =
11
1,
#110000
0,
#115000
1%
1J
0!
0N
0'
0H
06
01
1,
#120000
0,
#125000
b10 _
b100 ^
02
1,
#130000
0,
#135000
1!
1N
1'
1H
16
b10 4
b10 =
11
b100 ?
b100 0
b100 9
1,
#140000
0,
#145000
0'
0H
0!
0N
06
01
1,
#150000
0,
#155000
b11 _
b1000 ^
02
1,
#160000
0,
#165000
1'
1H
1!
1N
16
b11 4
b11 =
11
b1000 ?
b1000 0
b1000 9
1,
#170000
0,
#175000
0!
0N
0'
0H
06
01
1,
#180000
0,
#185000
b100 _
b1100 ^
02
1,
#190000
0,
#195000
1!
1N
1'
1H
16
b100 4
b100 =
11
b1100 ?
b1100 0
b1100 9
1,
#200000
0,
#205000
0'
0H
0!
0N
06
01
1,
#210000
0,
#215000
b101 _
b10000 ^
02
1,
#220000
0,
#225000
1'
1H
1!
1N
16
b101 4
b101 =
11
b10000 ?
b10000 0
b10000 9
1,
#230000
0,
#235000
0!
0N
0'
0H
06
01
1,
#240000
0,
#245000
b110 _
b10100 ^
02
1,
#250000
0,
#255000
1!
1N
1'
1H
16
b110 4
b110 =
11
b10100 ?
b10100 0
b10100 9
1,
#260000
0,
#265000
0'
0H
0!
0N
06
01
1,
#270000
0,
#275000
b111 _
b11000 ^
02
1,
#280000
0,
#285000
1'
1H
1!
1N
16
b111 4
b111 =
11
b11000 ?
b11000 0
b11000 9
1,
#290000
0,
#295000
0!
0N
0'
0H
06
01
1,
#300000
0,
#305000
b1000 _
b11100 ^
02
1,
#310000
0,
#315000
1!
1N
1'
1H
16
b1000 4
b1000 =
11
b11100 ?
b11100 0
b11100 9
1,
#320000
0,
#325000
0'
0H
0!
0N
06
01
1,
#330000
0,
#335000
b1001 _
b100000 ^
02
1,
#340000
0,
#345000
1'
1H
1!
1N
16
b1001 4
b1001 =
11
b100000 ?
b100000 0
b100000 9
1,
#350000
0,
#355000
0!
0N
0'
0H
06
01
1,
#360000
0,
#365000
02
1,
#370000
0,
#375000
1,
#380000
0,
#385000
1,
#390000
0,
#395000
1,
#400000
0,
#405000
1'
1H
1!
1N
16
b1 4
b1 =
11
b100100 ?
b100100 0
b100100 9
1,
b1 _
b100100 ^
#410000
0,
#415000
0!
0N
0'
0H
06
01
1,
#420000
0,
#425000
b10 _
b101000 ^
02
1,
#430000
0,
#435000
1!
1N
1'
1H
16
b10 4
b10 =
11
b101000 ?
b101000 0
b101000 9
1,
#440000
0,
#445000
0'
0H
0!
0N
06
01
1,
#450000
0,
#455000
b11 _
b101100 ^
02
1,
#460000
0,
#465000
1'
1H
1!
1N
16
b11 4
b11 =
11
b101100 ?
b101100 0
b101100 9
1,
#470000
0,
#475000
0!
0N
0'
0H
06
01
1,
#480000
0,
#485000
b100 _
b110000 ^
02
1,
#490000
0,
#495000
1!
1N
1'
1H
16
b100 4
b100 =
11
b110000 ?
b110000 0
b110000 9
1,
#500000
0,
#505000
0'
0H
0!
0N
06
01
1,
#510000
0,
#515000
b101 _
b110100 ^
02
1,
#520000
0,
#525000
1'
1H
1!
1N
16
b101 4
b101 =
11
b110100 ?
b110100 0
b110100 9
1,
#530000
0,
#535000
0!
0N
0'
0H
06
01
1,
#540000
0,
#545000
b110 _
b111000 ^
02
1,
#550000
0,
#555000
1!
1N
1'
1H
16
b110 4
b110 =
11
b111000 ?
b111000 0
b111000 9
1,
#560000
0,
#565000
0'
0H
0!
0N
06
01
1,
#570000
0,
#575000
b111 _
b111100 ^
02
1,
#580000
0,
#585000
1'
1H
1!
1N
16
b111 4
b111 =
11
b111100 ?
b111100 0
b111100 9
1,
#590000
0,
#595000
0!
0N
0'
0H
06
01
1,
#600000
0,
#605000
b1000 _
b1000000 ^
02
1,
#610000
0,
#615000
1!
1N
1'
1H
16
b1000 4
b1000 =
11
b1000000 ?
b1000000 0
b1000000 9
1,
#620000
0,
#625000
0'
0H
0!
0N
06
01
1,
#630000
0,
#635000
b1001 _
b1000100 ^
02
1,
#640000
0,
#645000
1'
1H
1!
1N
16
b1001 4
b1001 =
11
b1000100 ?
b1000100 0
b1000100 9
1,
#650000
0,
#655000
0!
0N
0'
0H
06
01
1,
#660000
0,
#665000
02
1,
#670000
0,
#675000
1,
#680000
0,
#685000
1,
#690000
0,
#695000
1,
#700000
0,
#705000
1'
1H
1!
1N
16
b1 4
b1 =
11
b1001000 ?
b1001000 0
b1001000 9
1,
b1 _
b1001000 ^
#710000
0,
#715000
0!
0N
0'
0H
06
01
1,
#720000
0,
#725000
b1001100 ^
02
1,
#730000
0,
#735000
1!
1N
1'
1H
16
11
b1001100 ?
b1001100 0
b1001100 9
1,
#740000
0,
#745000
0'
0H
0!
0N
06
01
1,
#750000
0,
#755000
02
1,
#760000
0,
#765000
1,
#770000
0,
#775000
1,
#780000
0,
#785000
1,
#790000
0,
#795000
1!
1N
1'
1H
16
11
b1010000 ?
b1010000 0
b1010000 9
1,
b1010000 ^
#800000
0,
#805000
0'
0H
0!
0N
06
01
1,
#810000
0,
#815000
02
1,
#820000
0,
#825000
1,
#830000
0,
#835000
1,
#840000
0,
#845000
1,
#850000
0,
#855000
1,
#860000
0,
#865000
1,
#870000
0,
#875000
1,
#880000
0,
#885000
1,
#890000
0,
#895000
b1010100 E
1(
1F
1/
b1010100 -
b1010100 8
1,
b1010100 \
#900000
0,
#905000
0(
0F
1"
1M
0/
1,
#910000
0,
#915000
b0 7
b0 ]
03
1,
