zynq/axi_lite_master.sv
`timescale 1ns / 1ps
//////////////////////////////////////////////////////////////////////////////////
// Company:
// Engineer: HDLForBeginners
//
// Module Name: axi_lite_master
// Client Project: HDLForBeginners
// Dependencies:
//
// Revision:
// Revision 0.01 - File Created
// Additional Comments:
//
//////////////////////////////////////////////////////////////////////////////////


module axi_lite_master
  #(
    parameter integer AXI_ADDR_WIDTH = 32,
    parameter integer AXI_DATA_WIDTH = 32
    )
   (
    input                                init_transaction,

    input wire                           M_AXI_ACLK,
    input wire                           M_AXI_ARESETN,

    // aw
    output wire [AXI_ADDR_WIDTH-1 : 0]   M_AXI_AWADDR,
    output wire [2 : 0]                  M_AXI_AWPROT,
    output wire                          M_AXI_AWVALID,
    input wire                           M_AXI_AWREADY,

    // w
    output wire [AXI_DATA_WIDTH-1 : 0]   M_AXI_WDATA,
    output wire [AXI_DATA_WIDTH/8-1 : 0] M_AXI_WSTRB,
    output wire                          M_AXI_WVALID,
    input wire                           M_AXI_WREADY,

    // b resp
    input wire [1 : 0]                   M_AXI_BRESP,
    input wire                           M_AXI_BVALID,
    output wire                          M_AXI_BREADY,

    // ar
    output wire [AXI_ADDR_WIDTH-1 : 0]   M_AXI_ARADDR,
    output wire [2 : 0]                  M_AXI_ARPROT,
    output wire                          M_AXI_ARVALID,
    input wire                           M_AXI_ARREADY,

    // r
    input wire [AXI_DATA_WIDTH-1 : 0]    M_AXI_RDATA,
    input wire [1 : 0]                   M_AXI_RRESP,
    input wire                           M_AXI_RVALID,
    output wire                          M_AXI_RREADY

    );

   // CAPITALS reserved for parameters and external signals.
   // internal signals are lowercase

   // why not parameter? can be accessed outside the module using module_instance_i.HSIZE
   // I don't want that, so localparam
   // Why don't I want that?
   // Not all of my parameters are designed to be changed by people outside
   // (don't know what they're for, valid ranges, etc).
   // generally parameters should be at the top if they're designed to be changed by users outside the module.
   localparam HSIZE = 640;
   localparam VSIZE = 480;


   // only include here signals that I drive (outputs). Inputs are not included (used later)


   // Why do I go to the effort of connecting up all of my outputs to duplicate internal outputs?!
   // I do this because the output signals are wires. Wires cannot be driven in an always_ff block,
   // If I want to drive these signals in a always block, I need to connect them up to logic signals first.
   // This is because the outputs are strictly OUTPUT signals. I can't use those signals in if statements
   // or combinitorial logic.
   // AFAIK this is a quirk of verilog/the syntesis tool. I think SystemVerilog is better with this now
   // but I'm demonstrating it here because it's the foolproof way of working with outputs.

   // aw
   logic [AXI_ADDR_WIDTH-1 : 0]          axi_awaddr;
   logic                                 axi_awvalid;

   // assign outputs to top level signals
   assign M_AXI_AWADDR = axi_awaddr;
   assign M_AXI_AWVALID = axi_awvalid;
   assign M_AXI_AWPROT =  0; // what's this? demonstrate going to find the answer

   // w
   logic [AXI_DATA_WIDTH-1 : 0]          axi_wdata;
   logic [AXI_DATA_WIDTH/8-1 : 0]        axi_wstrb;
   logic                                 axi_wvalid;
   assign M_AXI_WSTRB = axi_wstrb;
   assign M_AXI_WVALID = axi_wvalid;
   assign M_AXI_WDATA = axi_wdata;

   // b
   logic                                 axi_bready;
   logic                                 axi_berror;
   assign M_AXI_BREADY = axi_bready;

   // ar
   logic [AXI_ADDR_WIDTH-1 : 0]          axi_araddr;
   logic                                 axi_arvalid;
   assign M_AXI_ARADDR = axi_araddr;
   assign M_AXI_ARVALID = axi_arvalid;
   assign M_AXI_ARPROT = 0;

   // r
   logic [AXI_DATA_WIDTH-1 : 0]          axi_rready;
   logic                                 axi_rerror;
   assign M_AXI_RREADY = axi_rready;


   // These are all single-word transactions, so no LAST is needed.
   // It's implied the last is 1.

   // Write is done when b interface acknowledges write
   logic                                 write_done;
   assign write_done = axi_bready & M_AXI_BVALID; // BVALID is an input here

   logic                                 read_done;
   assign read_done = axi_rready & M_AXI_RVALID; // RVALID is alsoan input here


   // Write interfaces
   logic                                 init_transaction_i;

   // edge detect on input_fsync
   always_ff @(posedge M_AXI_ACLK)
     begin
        init_transaction_i <= init_transaction;
     end

   // This is how we do an edge detect.
   // Init WAS low (the delayed version has ~) and NOW it is NOT (so it went from 0 to 1).
   // This is a 1cc edge detect
   logic start;
   assign start = (init_transaction & ~init_transaction_i) ? 1 : 0;


   // State machine
   // write to registers
   typedef enum {IDLE, WR_REG_VDMACR, WR_REG_MM2S_HSIZE, WR_REG_MM2S_VSIZE, RD_REG_VDMACR, RD_REG_MM2S_HSIZE, RD_REG_MM2S_VSIZE}  my_state;

   my_state current_state = IDLE;
   my_state next_state    = IDLE;

   logic        start_write;
   logic        start_read;

   always_comb
     begin
        start_write = 0;
        start_read = 0;
        next_state  = current_state;

        case (current_state)
          IDLE   :
            begin
               if (start) begin
                  next_state  = WR_REG_VDMACR;
                  start_write = 1;

               end
            end
          WR_REG_VDMACR  :
            begin
               if (write_done) begin
                  next_state  = WR_REG_MM2S_HSIZE;
                  start_write = 1;

               end
            end
          WR_REG_MM2S_HSIZE   :
            begin
               if (write_done) begin
                  next_state = WR_REG_MM2S_VSIZE;
                  start_write = 1;

               end
            end
          WR_REG_MM2S_VSIZE   :
            begin
               if (write_done) begin
                  next_state = RD_REG_VDMACR;
                  start_read = 1;

               end
            end
          RD_REG_VDMACR  :
            begin
               if (read_done) begin
                  next_state = RD_REG_MM2S_HSIZE;
                  start_read = 1;

               end
            end
          RD_REG_MM2S_HSIZE   :
            begin
               if (read_done) begin
                  next_state = RD_REG_MM2S_VSIZE;
                  start_read = 1;

               end
            end
          RD_REG_MM2S_VSIZE   :
            begin
               if (read_done) begin
                  next_state = IDLE;

               end
            end
          default:
            next_state = current_state;

        endcase
     end

   // Register into next state
   always_ff @(posedge M_AXI_ACLK)
     begin
	    if(~M_AXI_ARESETN) begin
           current_state <= IDLE;
	    end
	    else begin
           current_state <= next_state;
	    end
     end

   // Define addresses and data values

   //aw
   always_comb
     begin
        axi_awaddr                         <= 0;
        case (current_state)
          WR_REG_VDMACR  :      axi_awaddr <= 'h30;
          WR_REG_MM2S_HSIZE   : axi_awaddr <= 'hA4;
          WR_REG_MM2S_VSIZE   : axi_awaddr <= 'hA0;
          default : axi_awaddr             <= 0;
        endcase
     end

   //w
   always_comb
     begin
        axi_wdata                         <= 0;
        case (current_state)
          WR_REG_VDMACR  :      axi_wdata <= 'h03;
          WR_REG_MM2S_HSIZE   : axi_wdata <= HSIZE;
          WR_REG_MM2S_VSIZE   : axi_wdata <= VSIZE;
          default : axi_wdata             <= 0;
        endcase
     end

   //ar
   always_comb
     begin
        axi_araddr                         <= 0;
        case (current_state)
          RD_REG_VDMACR  :      axi_araddr <= 'h30;
          RD_REG_MM2S_HSIZE   : axi_araddr <= 'hA4;
          RD_REG_MM2S_VSIZE   : axi_araddr <= 'hA0;
          default : axi_araddr             <= 0;
        endcase
     end

   //r expected values
   logic [AXI_DATA_WIDTH-1 : 0]    rdata_expected;
   always_comb
     begin
        rdata_expected                         <= 0;
        case (current_state)
          RD_REG_VDMACR  :      rdata_expected <= 'h03;
          RD_REG_MM2S_HSIZE   : rdata_expected <= HSIZE;
          RD_REG_MM2S_VSIZE   : rdata_expected <= VSIZE;
          default : rdata_expected             <= 0;
        endcase
     end

   // Address write interface
   always_ff @(posedge M_AXI_ACLK)
     begin
        // during reset, valid is low
	    if (M_AXI_ARESETN == 0 )
	      begin
	         axi_awvalid <= 1'b0;
	      end
	    else
	      begin
             // drive valid high at start of write
	         if (start_write)
	           begin
	              axi_awvalid <= 1'b1;
	           end

             // Having the inputs as capitals and outputs as lowercase really helps
             // in code clarity
             // In this if statement, I can see that the READY signal came in from outside
             // and the valid signal was driven by me.
             // At a glance I can ensure that I'm driving the correct signal
             // And ensure I'm checking the correct input signal.
             // hold high until ready is asserted
	         if (M_AXI_AWREADY && axi_awvalid)
	           begin
	              axi_awvalid <= 1'b0;
	           end
	      end
     end

   // Data write interface
   always_ff @(posedge M_AXI_ACLK)
     begin
        // during reset, valid is low
	    if (M_AXI_ARESETN == 0 )
	      begin
	         axi_wvalid <= 1'b0;
             axi_wstrb  <= 0;

	      end
	    else
	      begin
             // drive high at start of write
	         if (start_write)
	           begin
	              axi_wvalid <= 1'b1;
                  axi_wstrb <= 4'b1111; // strb all 1s
	           end

             // hold high until ready is asserted
	         if (M_AXI_WREADY && axi_wvalid)
	           begin
	              axi_wvalid <= 1'b0;
                  axi_wstrb  <= 0;
	           end
	      end
     end

   // Response channel with error check
   always_ff @(posedge M_AXI_ACLK)
     begin
        // during reset, ready is low
	    if (M_AXI_ARESETN == 0)
	      begin
	         axi_bready <= 1'b0;
             axi_berror <= 0;

	      end
        else begin
           // always be ready for response
           axi_bready <= 1'b1;

           // check error
	       if (M_AXI_BVALID && axi_bready) begin
              if (M_AXI_BRESP > 0) begin
                 axi_berror <= 1;
              end
              else begin
                 axi_berror <= 0;

              end
           end
        end
     end


   // Address read interface
   always_ff @(posedge M_AXI_ACLK)
     begin
        // during reset, valid is low
	    if (M_AXI_ARESETN == 0 )
	      begin
	         axi_arvalid <= 1'b0;
	      end
	    else
	      begin
             // drive valid high at start of write
	         if (start_read)
	           begin
	              axi_arvalid <= 1'b1;
	           end

	         if (M_AXI_ARREADY && axi_arvalid)
	           begin
	              axi_arvalid <= 1'b0;
	           end
	      end
     end

   // data read interface with error check
   always_ff @(posedge M_AXI_ACLK)
     begin
        // during reset, ready is low
	    if (M_AXI_ARESETN == 0)
	      begin
	         axi_rready <= 1'b0;
             axi_rerror <= 0;

	      end
        else begin
           // always be ready for data
           axi_rready <= 1'b1;

           // check error
	       if (M_AXI_RVALID && axi_rready) begin
              // if response is > 0
              if (M_AXI_RRESP > 0) begin
                 axi_rerror <= 1;
              end
              // or if data isn't what we expect
              else if (M_AXI_RDATA != rdata_expected) begin
                 axi_rerror <= 1;

              end
              else begin
                 axi_rerror <= 0;

              end
           end
        end
     end


endmodule

zynq/axi_lite_master_tb.sv
`timescale 1ns/1ns

//////////////////////////////////////////////////////////////////////////////////
// Company:
// Engineer: Stacey Rieck
//
// Create Date: 13.11.2021 14:32:12
// Design Name:
// Module Name: axi_lite_master_tb
// Project Name:
// Target Devices:
// Tool Versions:
// Description:
//
// Dependencies:
//
// Revision:
// Revision 0.01 - File Created
// Additional Comments:
//
//////////////////////////////////////////////////////////////////////////////////


module axi_lite_master_tb
  (   );

   logic CLK = 0;
   logic  RESET_N;

   localparam FREQUENCY = 50.0E6;
   localparam clk_period = (1/FREQUENCY)/1e-9;

   always begin
      CLK = #(clk_period/2) ~CLK;
   end

   initial
	 begin
        RESET_N=0;
		#100
          RESET_N=1;
	 end


   localparam AXI_ADDR_WIDTH = 32;
   localparam AXI_DATA_WIDTH = 32;

   wire [AXI_ADDR_WIDTH-1 : 0] M_AXI_AWADDR;
   wire [2 : 0]                M_AXI_AWPROT;
   wire                        M_AXI_AWVALID;
   wire                        M_AXI_AWREADY;

   // w
   wire [AXI_DATA_WIDTH-1 : 0] M_AXI_WDATA;
   wire [AXI_DATA_WIDTH/8-1 : 0] M_AXI_WSTRB;
   wire                          M_AXI_WVALID;
   wire                          M_AXI_WREADY;

   // b resp
   wire [1 : 0]                  M_AXI_BRESP;
   wire                          M_AXI_BVALID;
   wire                          M_AXI_BREADY;

   // ar
   wire [AXI_ADDR_WIDTH-1 : 0]   M_AXI_ARADDR;
   wire [2 : 0]                  M_AXI_ARPROT;
   wire                          M_AXI_ARVALID;
   wire                          M_AXI_ARREADY;

   // r
   wire [AXI_DATA_WIDTH-1 : 0]   M_AXI_RDATA;
   wire [1 : 0]                  M_AXI_RRESP;
   wire                          M_AXI_RVALID;
   wire                          M_AXI_RREADY;

   logic                         init_transaction;
   logic [31:0]                  init_counter;

   always_ff @(posedge CLK)
     begin
        if (~RESET_N) begin
           init_transaction <= 0;
           init_counter     <= 0;
        end
        else begin
           init_counter     <= init_counter+1;
           init_transaction <= 0;

           if (init_counter == 10) begin
              init_transaction <= 1;

           end
        end

     end

   axi_lite_master
     #(
       .AXI_ADDR_WIDTH(32),
       .AXI_DATA_WIDTH(32)
       )
   axi_lite_master_i
     (
      .init_transaction(init_transaction),

      .M_AXI_ACLK(CLK),
      .M_AXI_ARESETN(RESET_N),

      // aw
      .M_AXI_AWADDR(M_AXI_AWADDR),
      .M_AXI_AWPROT(M_AXI_AWPROT),
      .M_AXI_AWVALID(M_AXI_AWVALID),
      .M_AXI_AWREADY(M_AXI_AWREADY),

      // w
      .M_AXI_WDATA(M_AXI_WDATA),
      .M_AXI_WSTRB(M_AXI_WSTRB),
      .M_AXI_WVALID(M_AXI_WVALID),
      .M_AXI_WREADY(M_AXI_WREADY),

      // b resp
      .M_AXI_BRESP(M_AXI_BRESP),
      .M_AXI_BVALID(M_AXI_BVALID),
      .M_AXI_BREADY(M_AXI_BREADY),

      // ar
      .M_AXI_ARADDR(M_AXI_ARADDR),
      .M_AXI_ARPROT(M_AXI_ARPROT),
      .M_AXI_ARVALID(M_AXI_ARVALID),
      .M_AXI_ARREADY(M_AXI_ARREADY),

      // r
      .M_AXI_RDATA(M_AXI_RDATA),
      .M_AXI_RRESP(M_AXI_RRESP),
      .M_AXI_RVALID(M_AXI_RVALID),
      .M_AXI_RREADY(M_AXI_RREADY)

      );

    initial begin
        #500;
        $finish;
    end
    
    // Testbench procedure
    initial begin
        $dumpfile( "axi_lite_master_tb.vcd" );
        $dumpvars( 0, axi_lite_master_tb );
        #500;
        $finish;
    end
   // Zynq PS wrapper
   // Initialises PS subsystem
/*
   axi_vdma_0 axi_vdma_i
     (
      .s_axi_lite_aclk(CLK),        // input wire s_axi_lite_aclk
      .m_axi_mm2s_aclk(CLK),        // input wire m_axi_mm2s_aclk
      .m_axis_mm2s_aclk(CLK),      // input wire m_axis_mm2s_aclk
      .m_axi_s2mm_aclk(CLK),        // input wire m_axi_s2mm_aclk
      .s_axis_s2mm_aclk(CLK),      // input wire s_axis_s2mm_aclk
      .axi_resetn(RESET_N),                  // input wire axi_resetn
      .s_axi_lite_awvalid(M_AXI_AWVALID),  // input wire s_axi_lite_awvalid
      .s_axi_lite_awready(M_AXI_AWREADY),  // output wire s_axi_lite_awready
      .s_axi_lite_awaddr(M_AXI_AWADDR),    // input wire [8 : 0] s_axi_lite_awaddr
      .s_axi_lite_wvalid(M_AXI_WVALID),    // input wire s_axi_lite_wvalid
      .s_axi_lite_wready(M_AXI_WREADY),    // output wire s_axi_lite_wready
      .s_axi_lite_wdata(M_AXI_WDATA),      // input wire [31 : 0] s_axi_lite_wdata
      .s_axi_lite_bresp(M_AXI_BRESP),      // output wire [1 : 0] s_axi_lite_bresp
      .s_axi_lite_bvalid(M_AXI_BVALID),    // output wire s_axi_lite_bvalid
      .s_axi_lite_bready(M_AXI_BREADY),    // input wire s_axi_lite_bready
      .s_axi_lite_arvalid(M_AXI_ARVALID),  // input wire s_axi_lite_arvalid
      .s_axi_lite_arready(M_AXI_ARREADY),  // output wire s_axi_lite_arready
      .s_axi_lite_araddr(M_AXI_ARADDR),    // input wire [8 : 0] s_axi_lite_araddr
      .s_axi_lite_rvalid(M_AXI_RVALID),    // output wire s_axi_lite_rvalid
      .s_axi_lite_rready(M_AXI_RREADY),    // input wire s_axi_lite_rready
      .s_axi_lite_rdata(M_AXI_RDATA),      // output wire [31 : 0] s_axi_lite_rdata
      .s_axi_lite_rresp(M_AXI_RRESP)      // output wire [1 : 0] s_axi_lite_rresp
      );
*/

endmodule

zynq/axi_lite_master_tb.vcd
$date
	Fri May 31 15:55:26 2024
$end
$version
	Icarus Verilog
$end
$timescale
	1ps
$end
$scope module axi_lite_master_tb $end
$var wire 3 ! M_AXI_ARPROT [2:0] $end
$var wire 1 " M_AXI_ARREADY $end
$var wire 3 # M_AXI_AWPROT [2:0] $end
$var wire 1 $ M_AXI_AWREADY $end
$var wire 2 % M_AXI_BRESP [1:0] $end
$var wire 1 & M_AXI_BVALID $end
$var wire 32 ' M_AXI_RDATA [31:0] $end
$var wire 2 ( M_AXI_RRESP [1:0] $end
$var wire 1 ) M_AXI_RVALID $end
$var wire 1 * M_AXI_WREADY $end
$var wire 1 + M_AXI_WVALID $end
$var wire 4 , M_AXI_WSTRB [3:0] $end
$var wire 32 - M_AXI_WDATA [31:0] $end
$var wire 1 . M_AXI_RREADY $end
$var wire 1 / M_AXI_BREADY $end
$var wire 1 0 M_AXI_AWVALID $end
$var wire 32 1 M_AXI_AWADDR [31:0] $end
$var wire 1 2 M_AXI_ARVALID $end
$var wire 32 3 M_AXI_ARADDR [31:0] $end
$var parameter 32 4 AXI_ADDR_WIDTH $end
$var parameter 32 5 AXI_DATA_WIDTH $end
$var real 1 6 FREQUENCY $end
$var real 1 7 clk_period $end
$var reg 1 8 CLK $end
$var reg 1 9 RESET_N $end
$var reg 32 : init_counter [31:0] $end
$var reg 1 ; init_transaction $end
$scope module axi_lite_master_i $end
$var wire 1 8 M_AXI_ACLK $end
$var wire 32 < M_AXI_ARADDR [31:0] $end
$var wire 1 9 M_AXI_ARESETN $end
$var wire 3 = M_AXI_ARPROT [2:0] $end
$var wire 1 " M_AXI_ARREADY $end
$var wire 1 2 M_AXI_ARVALID $end
$var wire 32 > M_AXI_AWADDR [31:0] $end
$var wire 3 ? M_AXI_AWPROT [2:0] $end
$var wire 1 $ M_AXI_AWREADY $end
$var wire 1 0 M_AXI_AWVALID $end
$var wire 1 / M_AXI_BREADY $end
$var wire 2 @ M_AXI_BRESP [1:0] $end
$var wire 1 & M_AXI_BVALID $end
$var wire 32 A M_AXI_RDATA [31:0] $end
$var wire 2 B M_AXI_RRESP [1:0] $end
$var wire 1 ) M_AXI_RVALID $end
$var wire 32 C M_AXI_WDATA [31:0] $end
$var wire 1 * M_AXI_WREADY $end
$var wire 4 D M_AXI_WSTRB [3:0] $end
$var wire 1 + M_AXI_WVALID $end
$var wire 1 ; init_transaction $end
$var wire 1 E write_done $end
$var wire 1 F start $end
$var wire 1 G read_done $end
$var wire 1 . M_AXI_RREADY $end
$var parameter 32 H AXI_ADDR_WIDTH $end
$var parameter 32 I AXI_DATA_WIDTH $end
$var parameter 32 J HSIZE $end
$var parameter 32 K VSIZE $end
$var reg 32 L axi_araddr [31:0] $end
$var reg 1 M axi_arvalid $end
$var reg 32 N axi_awaddr [31:0] $end
$var reg 1 O axi_awvalid $end
$var reg 1 P axi_berror $end
$var reg 1 Q axi_bready $end
$var reg 1 R axi_rerror $end
$var reg 32 S axi_rready [31:0] $end
$var reg 32 T axi_wdata [31:0] $end
$var reg 4 U axi_wstrb [3:0] $end
$var reg 1 V axi_wvalid $end
$var reg 1 W init_transaction_i $end
$var reg 32 X rdata_expected [31:0] $end
$var reg 1 Y start_read $end
$var reg 1 Z start_write $end
$var integer 32 [ current_state [31:0] $end
$var integer 32 \ next_state [31:0] $end
$upscope $end
$upscope $end
$enddefinitions $end
$comment Show the parameter values. $end
$dumpall
b111100000 K
b1010000000 J
b100000 I
b100000 H
r20 7
r50000000 6
b100000 5
b100000 4
$end
#0
$dumpvars
b0 \
b0 [
0Z
0Y
b0 X
xW
xV
bx U
b0 T
bx S
xR
xQ
xP
xO
b0 N
xM
b0 L
xG
xF
xE
bx D
b0 C
bz B
bz A
bz @
b0 ?
b0 >
b0 =
b0 <
x;
bx :
09
08
b0 3
x2
b0 1
x0
x/
x.
b0 -
bx ,
x+
z*
z)
bz (
bz '
z&
bz %
z$
b0 #
z"
b0 !
$end
#10000
0F
0G
0E
0.
00
0O
b0 ,
b0 D
b0 U
0+
0V
0P
0/
0Q
02
0M
0R
b0 S
b0 :
0;
18
#20000
08
#30000
0W
18
#40000
08
#50000
18
#60000
08
#70000
18
#80000
08
#90000
18
#100000
08
19
#110000
xG
1.
xE
b1 :
b1 S
1/
1Q
18
#120000
08
#130000
b10 :
18
#140000
08
#150000
b11 :
18
#160000
08
#170000
b100 :
18
#180000
08
#190000
b101 :
18
#200000
08
#210000
b110 :
18
#220000
08
#230000
b111 :
18
#240000
08
#250000
b1000 :
18
#260000
08
#270000
b1001 :
18
#280000
08
#290000
b1010 :
18
#300000
08
#310000
1Z
b1 \
1F
1;
b1011 :
18
#320000
08
#330000
b110000 1
b110000 >
b110000 N
b11 -
b11 C
b11 T
0F
0Z
1W
b1 [
10
1O
b1111 ,
b1111 D
b1111 U
1+
1V
0;
b1100 :
18
#340000
08
#350000
b1101 :
0W
18
#360000
08
#370000
b1110 :
18
#380000
08
#390000
b1111 :
18
#400000
08
#410000
b10000 :
18
#420000
08
#430000
b10001 :
18
#440000
08
#450000
b10010 :
18
#460000
08
#470000
b10011 :
18
#480000
08
#490000
b10100 :
18
